[
  {
    "id": "everyday_rewards",
    "label": "Everyday Rewards",
    "shortLabel": "Everyday Rewards",
    "discountType": "direct_cpl",
    "centsPerLitre": 4,
    "maxLitresPerTransaction": 150,
    "maxTransactionsPer24h": 1,
    "excludedFuelTypes": ["AdBlue"],
    "notStackableWith": [],
    "requiresBarcode": true,
    "participatingStationScope": "participating EG Ampol and Ampol Foodary locations",
    "expiryDate": null,
    "lastVerifiedAt": "2026-07-04",
    "nextReviewAt": "2026-08-04",
    "sourceUrl": "https://www.everyday.com.au/rewards/partners/fuel.html",
    "stationBrands": ["EG Ampol", "Ampol Foodary"],
    "brandIncludes": ["eg ampol", "ampol foodary"]
  },
  {
    "id": "flybuys",
    "label": "Flybuys docket",
    "shortLabel": "Flybuys",
    "discountType": "direct_cpl",
    "centsPerLitre": 4,
    "maxLitresPerTransaction": 150,
    "maxTransactionsPer24h": 1,
    "excludedFuelTypes": ["AdBlue"],
    "notStackableWith": [],
    "requiresBarcode": true,
    "participatingStationScope": "participating Shell Reddy Express and Shell Coles Express locations",
    "expiryDate": null,
    "lastVerifiedAt": "2026-07-04",
    "nextReviewAt": "2026-08-04",
    "sourceUrl": "https://experience.flybuys.com.au/partners/shell-reddy-express/",
    "stationBrands": ["Shell Reddy Express", "Reddy Express", "Shell Coles Express"],
    "brandIncludes": ["shell", "reddy", "coles express"]
  },
  {
    "id": "gday_parks_shell",
    "label": "G'day Parks",
    "shortLabel": "G'day Parks",
    "discountType": "direct_cpl",
    "centsPerLitre": 4,
    "maxLitresPerTransaction": 150,
    "maxTransactionsPer24h": 1,
    "excludedFuelTypes": ["AdBlue"],
    "notStackableWith": [],
    "requiresBarcode": true,
    "participatingStationScope": "participating Shell Reddy Express and Shell-branded locations",
    "expiryDate": null,
    "lastVerifiedAt": "2026-07-04",
    "nextReviewAt": "2026-08-04",
    "sourceUrl": "https://gdayparks.com.au/terms-and-conditions/g-day-parks-fuel-offer-terms-and-conditions",
    "stationBrands": ["Shell Reddy Express", "Reddy Express"],
    "brandIncludes": ["shell", "reddy"]
  },
  {
    "id": "reddy_express_instore",
    "label": "Reddy Express in-store",
    "shortLabel": "Reddy Express in-store",
    "discountType": "direct_cpl",
    "centsPerLitre": 10,
    "maxLitresPerTransaction": 150,
    "maxTransactionsPer24h": 1,
    "excludedFuelTypes": ["AdBlue"],
    "notStackableWith": ["fleet_card", "shell_card", "motorcharge", "motorpass"],
    "requiresBarcode": false,
    "participatingStationScope": "participating Shell Reddy Express and Coles Express locations after eligible in-store spend",
    "expiryDate": null,
    "lastVerifiedAt": "2026-07-04",
    "nextReviewAt": "2026-08-04",
    "sourceUrl": "https://www.reddyexpress.com.au/terms-and-conditions/spend-20-get-10-cents-per-litre-fuel-discount",
    "stationBrands": ["Shell Reddy Express", "Reddy Express", "Coles Express"],
    "brandIncludes": ["shell", "reddy", "coles express"]
  },
  {
    "id": "nrma_ampol",
    "label": "NRMA / Ampol",
    "shortLabel": "NRMA / Ampol",
    "discountType": "direct_cpl",
    "centsPerLitre": 5,
    "fuelTypeCentsPerLitre": {
      "E10": 4,
      "U91": 4,
      "P95": 5,
      "P98": 5,
      "DL": 4,
      "PDL": 5
    },
    "maxLitresPerTransaction": 150,
    "maxTransactionsPer24h": 1,
    "excludedFuelTypes": ["AdBlue"],
    "notStackableWith": [],
    "requiresBarcode": true,
    "participatingStationScope": "participating Ampol Foodary locations",
    "expiryDate": null,
    "lastVerifiedAt": "2026-07-04",
    "nextReviewAt": "2026-08-04",
    "sourceUrl": "https://www.mynrma.com.au/membership/benefits/ampol",
    "stationBrands": ["Ampol Foodary", "participating Ampol"],
    "brandIncludes": ["ampol foodary"]
  },
  {
    "id": "racv_eg_ampol",
    "label": "RACV / EG Ampol",
    "shortLabel": "RACV / EG Ampol",
    "discountType": "direct_cpl",
    "centsPerLitre": 5,
    "maxLitresPerTransaction": 150,
    "maxTransactionsPer24h": 1,
    "excludedFuelTypes": ["LPG"],
    "notStackableWith": ["fuel_card"],
    "requiresBarcode": true,
    "participatingStationScope": "participating EG Ampol co-branded locations",
    "expiryDate": null,
    "lastVerifiedAt": "2026-07-04",
    "nextReviewAt": "2026-08-04",
    "sourceUrl": "https://www.racv.com.au/membership/member-discounts/motoring/fuel-vouchers.html",
    "stationBrands": ["EG Ampol"],
    "brandIncludes": ["eg ampol"]
  },
  {
    "id": "racq_caltex",
    "label": "RACQ / Caltex",
    "shortLabel": "RACQ / Caltex",
    "discountType": "direct_cpl",
    "centsPerLitre": 4,
    "maxLitresPerTransaction": 120,
    "maxTransactionsPer24h": 1,
    "excludedFuelTypes": [],
    "notStackableWith": [],
    "requiresBarcode": true,
    "participatingStationScope": "participating Caltex locations",
    "expiryDate": null,
    "lastVerifiedAt": "2026-07-04",
    "nextReviewAt": "2026-08-04",
    "sourceUrl": "https://www.racq.com.au/membership/benefits-and-discounts/car-and-fuel/caltex",
    "stationBrands": ["Caltex"],
    "brandIncludes": ["caltex"]
  },
  {
    "id": "rac_wa_caltex",
    "label": "RAC WA",
    "shortLabel": "RAC WA",
    "discountType": "direct_cpl",
    "centsPerLitre": 4,
    "maxLitresPerTransaction": 120,
    "maxTransactionsPer24h": 1,
    "excludedFuelTypes": [],
    "notStackableWith": [],
    "requiresBarcode": true,
    "participatingStationScope": "participating Caltex and Better Choice locations",
    "expiryDate": null,
    "lastVerifiedAt": "2026-07-04",
    "nextReviewAt": "2026-08-04",
    "sourceUrl": "https://rac.com.au/membership-benefits/discounts-and-special-offers/member-benefit-caltex",
    "stationBrands": ["Caltex", "Better Choice"],
    "brandIncludes": ["caltex", "better choice"]
  },
  {
    "id": "raa_sa_fuel",
    "label": "RAA SA",
    "shortLabel": "RAA SA",
    "discountType": "direct_cpl",
    "centsPerLitre": 10,
    "maxLitresPerTransaction": 120,
    "maxTransactionsPer24h": 1,
    "excludedFuelTypes": [],
    "notStackableWith": [],
    "requiresBarcode": true,
    "participatingStationScope": "participating South Australian fuel stations",
    "expiryDate": null,
    "lastVerifiedAt": "2026-07-04",
    "nextReviewAt": "2026-08-04",
    "sourceUrl": "https://our.raa.com.au/membership/member-discounts-and-offers/fuel-discounts",
    "stationBrands": ["participating SA fuel stations", "Caltex"],
    "brandIncludes": ["caltex"],
    "includedStates": ["SA"]
  },
  {
    "id": "linkt_7eleven",
    "label": "Linkt Rewards",
    "shortLabel": "Linkt / 7-Eleven",
    "discountType": "direct_cpl",
    "centsPerLitre": 6,
    "maxLitresPerTransaction": 120,
    "maxTransactionsPer24h": 2,
    "excludedFuelTypes": ["LPG", "AdBlue"],
    "notStackableWith": ["7eleven_fuel_lock", "7eleven_app_offer", "fuel_card"],
    "requiresBarcode": true,
    "participatingStationScope": "participating 7-Eleven fuel stores",
    "expiryDate": null,
    "lastVerifiedAt": "2026-07-04",
    "nextReviewAt": "2026-08-04",
    "sourceUrl": "https://www.linkt.com.au/legal/rewards/7-eleven.html",
    "stationBrands": ["7-Eleven"],
    "brandIncludes": ["7-eleven", "seven eleven"]
  },
  {
    "id": "telstra_plus_7eleven",
    "label": "Telstra Plus",
    "shortLabel": "Telstra Plus",
    "discountType": "direct_cpl",
    "centsPerLitre": 6,
    "maxLitresPerTransaction": 100,
    "maxTransactionsPer24h": 2,
    "excludedFuelTypes": ["LPG", "AdBlue"],
    "notStackableWith": ["7eleven_fuel_lock", "7eleven_app_offer", "fuel_card"],
    "requiresBarcode": true,
    "participatingStationScope": "participating 7-Eleven fuel stores",
    "expiryDate": null,
    "lastVerifiedAt": "2026-07-04",
    "nextReviewAt": "2026-08-04",
    "sourceUrl": "https://www.telstra.com.au/plus/benefits/7-eleven",
    "stationBrands": ["7-Eleven"],
    "brandIncludes": ["7-eleven", "seven eleven"]
  },
  {
    "id": "wilson_parking_7eleven",
    "label": "Wilson Parking",
    "shortLabel": "Wilson Parking",
    "discountType": "direct_cpl",
    "centsPerLitre": 6,
    "maxLitresPerTransaction": 100,
    "maxTransactionsPer24h": 2,
    "excludedFuelTypes": ["LPG", "AdBlue"],
    "excludedStates": ["SA", "TAS"],
    "notStackableWith": ["7eleven_fuel_lock", "7eleven_app_offer", "fuel_card"],
    "requiresBarcode": true,
    "participatingStationScope": "participating 7-Eleven fuel stores except South Australia and Tasmania",
    "expiryDate": null,
    "lastVerifiedAt": "2026-07-04",
    "nextReviewAt": "2026-08-04",
    "sourceUrl": "https://www.wilsonparking.com.au/apps/perks/",
    "stationBrands": ["7-Eleven"],
    "brandIncludes": ["7-eleven", "seven eleven"]
  },
  {
    "id": "nab_goodies_7eleven",
    "label": "NAB Goodies",
    "shortLabel": "NAB Goodies",
    "discountType": "direct_cpl",
    "centsPerLitre": 10,
    "maxLitresPerTransaction": 100,
    "maxTransactionsPer24h": 2,
    "excludedFuelTypes": ["LPG", "AdBlue"],
    "notStackableWith": ["7eleven_fuel_lock", "7eleven_app_offer", "fuel_card"],
    "requiresBarcode": true,
    "participatingStationScope": "participating 7-Eleven fuel stores",
    "expiryDate": "2026-09-30",
    "lastVerifiedAt": "2026-07-04",
    "nextReviewAt": "2026-08-04",
    "sourceUrl": "https://www.nab.com.au/personal/goodies",
    "stationBrands": ["7-Eleven"],
    "brandIncludes": ["7-eleven", "seven eleven"]
  }
]
